xbdown.py
xbdown-3.0.0.dist-info/METADATA
xbdown-3.0.0.dist-info/WHEEL
xbdown-3.0.0.dist-info/entry_points.txt
xbdown-3.0.0.dist-info/top_level.txt
xbdown-3.0.0.dist-info/RECORD
